{"nodes": [{"id": "learningappservice", "label": "LearningAppService.cs", "file_type": "code", "source_file": "src/KnowledgeHub.Application/Learning/LearningAppService.cs", "source_location": "L1"}, {"id": "learningappservice_learningappservice", "label": "LearningAppService", "file_type": "code", "source_file": "src/KnowledgeHub.Application/Learning/LearningAppService.cs", "source_location": "L14"}, {"id": "applicationservice", "label": "ApplicationService", "file_type": "code", "source_file": "", "source_location": ""}, {"id": "ilearningappservice", "label": "ILearningAppService", "file_type": "code", "source_file": "", "source_location": ""}, {"id": "learningappservice_learningappservice_getdashboardasync", "label": ".GetDashboardAsync()", "file_type": "code", "source_file": "src/KnowledgeHub.Application/Learning/LearningAppService.cs", "source_location": "L36"}, {"id": "learningappservice_learningappservice_getmycoursesasync", "label": ".GetMyCoursesAsync()", "file_type": "code", "source_file": "src/KnowledgeHub.Application/Learning/LearningAppService.cs", "source_location": "L86"}, {"id": "learningappservice_learningappservice_getprogressasync", "label": ".GetProgressAsync()", "file_type": "code", "source_file": "src/KnowledgeHub.Application/Learning/LearningAppService.cs", "source_location": "L120"}, {"id": "learningappservice_learningappservice_recordprogressasync", "label": ".RecordProgressAsync()", "file_type": "code", "source_file": "src/KnowledgeHub.Application/Learning/LearningAppService.cs", "source_location": "L140"}, {"id": "learningappservice_learningappservice_getknowledgemasteryasync", "label": ".GetKnowledgeMasteryAsync()", "file_type": "code", "source_file": "src/KnowledgeHub.Application/Learning/LearningAppService.cs", "source_location": "L184"}], "edges": [{"source": "learningappservice", "target": "system", "relation": "imports", "confidence": "EXTRACTED", "source_file": "src/KnowledgeHub.Application/Learning/LearningAppService.cs", "source_location": "L1", "weight": 1.0}, {"source": "learningappservice", "target": "generic", "relation": "imports", "confidence": "EXTRACTED", "source_file": "src/KnowledgeHub.Application/Learning/LearningAppService.cs", "source_location": "L2", "weight": 1.0}, {"source": "learningappservice", "target": "linq", "relation": "imports", "confidence": "EXTRACTED", "source_file": "src/KnowledgeHub.Application/Learning/LearningAppService.cs", "source_location": "L3", "weight": 1.0}, {"source": "learningappservice", "target": "tasks", "relation": "imports", "confidence": "EXTRACTED", "source_file": "src/KnowledgeHub.Application/Learning/LearningAppService.cs", "source_location": "L4", "weight": 1.0}, {"source": "learningappservice", "target": "courses", "relation": "imports", "confidence": "EXTRACTED", "source_file": "src/KnowledgeHub.Application/Learning/LearningAppService.cs", "source_location": "L5", "weight": 1.0}, {"source": "learningappservice", "target": "dtos", "relation": "imports", "confidence": "EXTRACTED", "source_file": "src/KnowledgeHub.Application/Learning/LearningAppService.cs", "source_location": "L6", "weight": 1.0}, {"source": "learningappservice", "target": "enums", "relation": "imports", "confidence": "EXTRACTED", "source_file": "src/KnowledgeHub.Application/Learning/LearningAppService.cs", "source_location": "L7", "weight": 1.0}, {"source": "learningappservice", "target": "services", "relation": "imports", "confidence": "EXTRACTED", "source_file": "src/KnowledgeHub.Application/Learning/LearningAppService.cs", "source_location": "L8", "weight": 1.0}, {"source": "learningappservice", "target": "repositories", "relation": "imports", "confidence": "EXTRACTED", "source_file": "src/KnowledgeHub.Application/Learning/LearningAppService.cs", "source_location": "L9", "weight": 1.0}, {"source": "learningappservice", "target": "users", "relation": "imports", "confidence": "EXTRACTED", "source_file": "src/KnowledgeHub.Application/Learning/LearningAppService.cs", "source_location": "L10", "weight": 1.0}, {"source": "learningappservice", "target": "learningappservice_learningappservice", "relation": "contains", "confidence": "EXTRACTED", "source_file": "src/KnowledgeHub.Application/Learning/LearningAppService.cs", "source_location": "L14", "weight": 1.0}, {"source": "learningappservice_learningappservice", "target": "applicationservice", "relation": "inherits", "confidence": "EXTRACTED", "source_file": "src/KnowledgeHub.Application/Learning/LearningAppService.cs", "source_location": "L14", "weight": 1.0}, {"source": "learningappservice_learningappservice", "target": "ilearningappservice", "relation": "inherits", "confidence": "EXTRACTED", "source_file": "src/KnowledgeHub.Application/Learning/LearningAppService.cs", "source_location": "L14", "weight": 1.0}, {"source": "learningappservice_learningappservice", "target": "learningappservice_learningappservice_getdashboardasync", "relation": "method", "confidence": "EXTRACTED", "source_file": "src/KnowledgeHub.Application/Learning/LearningAppService.cs", "source_location": "L36", "weight": 1.0}, {"source": "learningappservice_learningappservice", "target": "learningappservice_learningappservice_getmycoursesasync", "relation": "method", "confidence": "EXTRACTED", "source_file": "src/KnowledgeHub.Application/Learning/LearningAppService.cs", "source_location": "L86", "weight": 1.0}, {"source": "learningappservice_learningappservice", "target": "learningappservice_learningappservice_getprogressasync", "relation": "method", "confidence": "EXTRACTED", "source_file": "src/KnowledgeHub.Application/Learning/LearningAppService.cs", "source_location": "L120", "weight": 1.0}, {"source": "learningappservice_learningappservice", "target": "learningappservice_learningappservice_recordprogressasync", "relation": "method", "confidence": "EXTRACTED", "source_file": "src/KnowledgeHub.Application/Learning/LearningAppService.cs", "source_location": "L140", "weight": 1.0}, {"source": "learningappservice_learningappservice", "target": "learningappservice_learningappservice_getknowledgemasteryasync", "relation": "method", "confidence": "EXTRACTED", "source_file": "src/KnowledgeHub.Application/Learning/LearningAppService.cs", "source_location": "L184", "weight": 1.0}]}