{"nodes": [{"id": "studentcourseappservice", "label": "StudentCourseAppService.cs", "file_type": "code", "source_file": "src/KnowledgeHub.Application/Courses/StudentCourseAppService.cs", "source_location": "L1"}, {"id": "studentcourseappservice_studentcourseappservice", "label": "StudentCourseAppService", "file_type": "code", "source_file": "src/KnowledgeHub.Application/Courses/StudentCourseAppService.cs", "source_location": "L20"}, {"id": "knowledgehubappservice", "label": "KnowledgeHubAppService", "file_type": "code", "source_file": "", "source_location": ""}, {"id": "istudentcourseappservice", "label": "IStudentCourseAppService", "file_type": "code", "source_file": "", "source_location": ""}, {"id": "studentcourseappservice_studentcourseappservice_resolvetenantfilter", "label": ".ResolveTenantFilter()", "file_type": "code", "source_file": "src/KnowledgeHub.Application/Courses/StudentCourseAppService.cs", "source_location": "L47"}, {"id": "studentcourseappservice_studentcourseappservice_getpagedasync", "label": ".GetPagedAsync()", "file_type": "code", "source_file": "src/KnowledgeHub.Application/Courses/StudentCourseAppService.cs", "source_location": "L54"}, {"id": "studentcourseappservice_studentcourseappservice_getavailablestudentsasync", "label": ".GetAvailableStudentsAsync()", "file_type": "code", "source_file": "src/KnowledgeHub.Application/Courses/StudentCourseAppService.cs", "source_location": "L119"}, {"id": "studentcourseappservice_studentcourseappservice_enrollstudentasync", "label": ".EnrollStudentAsync()", "file_type": "code", "source_file": "src/KnowledgeHub.Application/Courses/StudentCourseAppService.cs", "source_location": "L197"}, {"id": "studentcourseappservice_studentcourseappservice_batchenrollasync", "label": ".BatchEnrollAsync()", "file_type": "code", "source_file": "src/KnowledgeHub.Application/Courses/StudentCourseAppService.cs", "source_location": "L232"}, {"id": "studentcourseappservice_studentcourseappservice_deleteasync", "label": ".DeleteAsync()", "file_type": "code", "source_file": "src/KnowledgeHub.Application/Courses/StudentCourseAppService.cs", "source_location": "L280"}, {"id": "studentcourseappservice_studentcourseappservice_getstudenttenantidasync", "label": ".GetStudentTenantIdAsync()", "file_type": "code", "source_file": "src/KnowledgeHub.Application/Courses/StudentCourseAppService.cs", "source_location": "L293"}, {"id": "studentcourseappservice_studentcourseappservice_getstudenttenantidsasync", "label": ".GetStudentTenantIdsAsync()", "file_type": "code", "source_file": "src/KnowledgeHub.Application/Courses/StudentCourseAppService.cs", "source_location": "L302"}], "edges": [{"source": "studentcourseappservice", "target": "system", "relation": "imports", "confidence": "EXTRACTED", "source_file": "src/KnowledgeHub.Application/Courses/StudentCourseAppService.cs", "source_location": "L1", "weight": 1.0}, {"source": "studentcourseappservice", "target": "generic", "relation": "imports", "confidence": "EXTRACTED", "source_file": "src/KnowledgeHub.Application/Courses/StudentCourseAppService.cs", "source_location": "L2", "weight": 1.0}, {"source": "studentcourseappservice", "target": "linq", "relation": "imports", "confidence": "EXTRACTED", "source_file": "src/KnowledgeHub.Application/Courses/StudentCourseAppService.cs", "source_location": "L3", "weight": 1.0}, {"source": "studentcourseappservice", "target": "tasks", "relation": "imports", "confidence": "EXTRACTED", "source_file": "src/KnowledgeHub.Application/Courses/StudentCourseAppService.cs", "source_location": "L4", "weight": 1.0}, {"source": "studentcourseappservice", "target": "dtos", "relation": "imports", "confidence": "EXTRACTED", "source_file": "src/KnowledgeHub.Application/Courses/StudentCourseAppService.cs", "source_location": "L5", "weight": 1.0}, {"source": "studentcourseappservice", "target": "learning", "relation": "imports", "confidence": "EXTRACTED", "source_file": "src/KnowledgeHub.Application/Courses/StudentCourseAppService.cs", "source_location": "L6", "weight": 1.0}, {"source": "studentcourseappservice", "target": "enums", "relation": "imports", "confidence": "EXTRACTED", "source_file": "src/KnowledgeHub.Application/Courses/StudentCourseAppService.cs", "source_location": "L7", "weight": 1.0}, {"source": "studentcourseappservice", "target": "permissions", "relation": "imports", "confidence": "EXTRACTED", "source_file": "src/KnowledgeHub.Application/Courses/StudentCourseAppService.cs", "source_location": "L8", "weight": 1.0}, {"source": "studentcourseappservice", "target": "authorization", "relation": "imports", "confidence": "EXTRACTED", "source_file": "src/KnowledgeHub.Application/Courses/StudentCourseAppService.cs", "source_location": "L9", "weight": 1.0}, {"source": "studentcourseappservice", "target": "entityframeworkcore", "relation": "imports", "confidence": "EXTRACTED", "source_file": "src/KnowledgeHub.Application/Courses/StudentCourseAppService.cs", "source_location": "L10", "weight": 1.0}, {"source": "studentcourseappservice", "target": "abp", "relation": "imports", "confidence": "EXTRACTED", "source_file": "src/KnowledgeHub.Application/Courses/StudentCourseAppService.cs", "source_location": "L11", "weight": 1.0}, {"source": "studentcourseappservice", "target": "dtos", "relation": "imports", "confidence": "EXTRACTED", "source_file": "src/KnowledgeHub.Application/Courses/StudentCourseAppService.cs", "source_location": "L12", "weight": 1.0}, {"source": "studentcourseappservice", "target": "data", "relation": "imports", "confidence": "EXTRACTED", "source_file": "src/KnowledgeHub.Application/Courses/StudentCourseAppService.cs", "source_location": "L13", "weight": 1.0}, {"source": "studentcourseappservice", "target": "repositories", "relation": "imports", "confidence": "EXTRACTED", "source_file": "src/KnowledgeHub.Application/Courses/StudentCourseAppService.cs", "source_location": "L14", "weight": 1.0}, {"source": "studentcourseappservice", "target": "identity", "relation": "imports", "confidence": "EXTRACTED", "source_file": "src/KnowledgeHub.Application/Courses/StudentCourseAppService.cs", "source_location": "L15", "weight": 1.0}, {"source": "studentcourseappservice", "target": "multitenancy", "relation": "imports", "confidence": "EXTRACTED", "source_file": "src/KnowledgeHub.Application/Courses/StudentCourseAppService.cs", "source_location": "L16", "weight": 1.0}, {"source": "studentcourseappservice", "target": "studentcourseappservice_studentcourseappservice", "relation": "contains", "confidence": "EXTRACTED", "source_file": "src/KnowledgeHub.Application/Courses/StudentCourseAppService.cs", "source_location": "L20", "weight": 1.0}, {"source": "studentcourseappservice_studentcourseappservice", "target": "knowledgehubappservice", "relation": "inherits", "confidence": "EXTRACTED", "source_file": "src/KnowledgeHub.Application/Courses/StudentCourseAppService.cs", "source_location": "L20", "weight": 1.0}, {"source": "studentcourseappservice_studentcourseappservice", "target": "istudentcourseappservice", "relation": "inherits", "confidence": "EXTRACTED", "source_file": "src/KnowledgeHub.Application/Courses/StudentCourseAppService.cs", "source_location": "L20", "weight": 1.0}, {"source": "studentcourseappservice_studentcourseappservice", "target": "studentcourseappservice_studentcourseappservice_resolvetenantfilter", "relation": "method", "confidence": "EXTRACTED", "source_file": "src/KnowledgeHub.Application/Courses/StudentCourseAppService.cs", "source_location": "L47", "weight": 1.0}, {"source": "studentcourseappservice_studentcourseappservice", "target": "studentcourseappservice_studentcourseappservice_getpagedasync", "relation": "method", "confidence": "EXTRACTED", "source_file": "src/KnowledgeHub.Application/Courses/StudentCourseAppService.cs", "source_location": "L54", "weight": 1.0}, {"source": "studentcourseappservice_studentcourseappservice", "target": "studentcourseappservice_studentcourseappservice_getavailablestudentsasync", "relation": "method", "confidence": "EXTRACTED", "source_file": "src/KnowledgeHub.Application/Courses/StudentCourseAppService.cs", "source_location": "L119", "weight": 1.0}, {"source": "studentcourseappservice_studentcourseappservice", "target": "studentcourseappservice_studentcourseappservice_enrollstudentasync", "relation": "method", "confidence": "EXTRACTED", "source_file": "src/KnowledgeHub.Application/Courses/StudentCourseAppService.cs", "source_location": "L197", "weight": 1.0}, {"source": "studentcourseappservice_studentcourseappservice", "target": "studentcourseappservice_studentcourseappservice_batchenrollasync", "relation": "method", "confidence": "EXTRACTED", "source_file": "src/KnowledgeHub.Application/Courses/StudentCourseAppService.cs", "source_location": "L232", "weight": 1.0}, {"source": "studentcourseappservice_studentcourseappservice", "target": "studentcourseappservice_studentcourseappservice_deleteasync", "relation": "method", "confidence": "EXTRACTED", "source_file": "src/KnowledgeHub.Application/Courses/StudentCourseAppService.cs", "source_location": "L280", "weight": 1.0}, {"source": "studentcourseappservice_studentcourseappservice", "target": "studentcourseappservice_studentcourseappservice_getstudenttenantidasync", "relation": "method", "confidence": "EXTRACTED", "source_file": "src/KnowledgeHub.Application/Courses/StudentCourseAppService.cs", "source_location": "L293", "weight": 1.0}, {"source": "studentcourseappservice_studentcourseappservice", "target": "studentcourseappservice_studentcourseappservice_getstudenttenantidsasync", "relation": "method", "confidence": "EXTRACTED", "source_file": "src/KnowledgeHub.Application/Courses/StudentCourseAppService.cs", "source_location": "L302", "weight": 1.0}, {"source": "studentcourseappservice_studentcourseappservice_getpagedasync", "target": "studentcourseappservice_studentcourseappservice_resolvetenantfilter", "relation": "calls", "confidence": "EXTRACTED", "source_file": "src/KnowledgeHub.Application/Courses/StudentCourseAppService.cs", "source_location": "L57", "weight": 1.0}, {"source": "studentcourseappservice_studentcourseappservice_getavailablestudentsasync", "target": "studentcourseappservice_studentcourseappservice_resolvetenantfilter", "relation": "calls", "confidence": "EXTRACTED", "source_file": "src/KnowledgeHub.Application/Courses/StudentCourseAppService.cs", "source_location": "L122", "weight": 1.0}, {"source": "studentcourseappservice_studentcourseappservice_enrollstudentasync", "target": "studentcourseappservice_studentcourseappservice_getstudenttenantidasync", "relation": "calls", "confidence": "EXTRACTED", "source_file": "src/KnowledgeHub.Application/Courses/StudentCourseAppService.cs", "source_location": "L224", "weight": 1.0}, {"source": "studentcourseappservice_studentcourseappservice_batchenrollasync", "target": "studentcourseappservice_studentcourseappservice_getstudenttenantidsasync", "relation": "calls", "confidence": "EXTRACTED", "source_file": "src/KnowledgeHub.Application/Courses/StudentCourseAppService.cs", "source_location": "L257", "weight": 1.0}]}